[
{"uuid":"B9407F30-F5F8-466E-AFF9-25556B57FE6D","major_id":"43853","minor_id":"11904","categories":["baby care","bakery product","beverage","cleaning supplies","condiments","cooking products","diary"]},
{"uuid":"B9407F30-F5F8-466E-AFF9-25556B57FE6D","major_id":"55438","minor_id":"24385","categories":["desserts","electronics","fresh fruits", "fruits","health & sanitory", "kitchen supplies"]},
{"uuid":"B9407F30-F5F8-466E-AFF9-25556B57FE6D","major_id":"12254","minor_id":"42356","categories":["liquor","other","packaged items","pet care", "polutry","snacks","veggies"]},
]